transactions_analysis_sk24/__init__.py
transactions_analysis_sk24/__main__.py
transactions_analysis_sk24/analyzer.py
transactions_analysis_sk24-0.1.0.dist-info/METADATA
transactions_analysis_sk24-0.1.0.dist-info/WHEEL
transactions_analysis_sk24-0.1.0.dist-info/top_level.txt
transactions_analysis_sk24-0.1.0.dist-info/RECORD
